returncache.py
returncache-1.0.0.dist-info/METADATA
returncache-1.0.0.dist-info/WHEEL
returncache-1.0.0.dist-info/licenses/LICENSE
returncache-1.0.0.dist-info/RECORD
