Metadata-Version: 2.4
Name: returncache
Version: 1.0.0
Summary: A decorator for wrapping any function in an expiring cache. Supports coroutines!
Project-URL: Source, https://github.com/gingershaped/returncache
Project-URL: Issues, https://github.com/gingershaped/returncache/issues
Author: Ginger
License-Expression: MPL-2.0
License-File: LICENSE
Classifier: Operating System :: OS Independent
Classifier: Programming Language :: Python :: 3
Requires-Python: >=3.12
